README.md
setup.py
bin/fly-grackle.py
bin/grackle-wrapper.py
grackle/__init__.py
grackle/log.py
grackle/main.py
grackle/state.py
grackle.egg-info/PKG-INFO
grackle.egg-info/SOURCES.txt
grackle.egg-info/dependency_links.txt
grackle.egg-info/not-zip-safe
grackle.egg-info/top_level.txt
grackle/paramils/__init__.py
grackle/paramils/reparamils.py
grackle/paramils/results.py
grackle/runner/__init__.py
grackle/runner/eprover.py
grackle/runner/premise.py
grackle/runner/runner.py
grackle/trainer/__init__.py
grackle/trainer/premise.py
grackle/trainer/trainer.py
grackle/trainer/eprover/__init__.py
grackle/trainer/eprover/domain.py
grackle/trainer/eprover/trainer.py
grackle/trainer/eprover/tuner.py
grackle/trainer/eprover/wpo.py
paramils/algo_specifics.rb
paramils/global_helper.rb
paramils/param_ils_2_3_run.rb
paramils/param_reader.rb
paramils/stats_ils.rb