Metadata-Version: 1.0
Name: grackle
Version: 0.1
Summary: Grackle: Configuration Collection Invention System
Home-page: http://github.com/ai4reason/grackle
Author: cbboyan
Author-email: UNKNOWN
License: GPL3
Platform: UNKNOWN
